winsdk_toast/__init__.py
winsdk_toast/event.py
winsdk_toast/notifier.py
winsdk_toast/toast.py
winsdk_toast-0.1.0.dist-info/LICENSE
winsdk_toast-0.1.0.dist-info/METADATA
winsdk_toast-0.1.0.dist-info/WHEEL
winsdk_toast-0.1.0.dist-info/top_level.txt
winsdk_toast-0.1.0.dist-info/RECORD
