Metadata-Version: 2.1
Name: winsdk-toast
Version: 0.1.0
Summary: A simple package for displaying Windows Toast Notification based on winsdk.
Home-page: https://github.com/Mo-Dabao/winsdk_toast
Author: modabao
Author-email: mo_dabao@qq.com
Classifier: Operating System :: Microsoft :: Windows :: Windows 10
Classifier: License :: OSI Approved :: MIT License
Requires-Python: >=3.5
License-File: LICENSE
Requires-Dist: winsdk
